[
    {
        "term": 1,
        "command": "NO-OP",
        "key": "None",
        "value": "None"
    },
    {
        "term": 1,
        "command": "SET",
        "key": "1",
        "value": "1"
    },
    {
        "term": 1,
        "command": "SET",
        "key": "2",
        "value": "2"
    },
    {
        "term": 1,
        "command": "SET",
        "key": "3",
        "value": "3"
    },
    {
        "term": 1,
        "command": "SET",
        "key": "4",
        "value": "4"
    },
    {
        "term": 1,
        "command": "SET",
        "key": "5",
        "value": "5"
    },
    {
        "term": 1,
        "command": "SET",
        "key": "6",
        "value": "6"
    },
    {
        "term": 2,
        "command": "NO-OP",
        "key": "None",
        "value": "None"
    },
    {
        "term": 2,
        "command": "SET",
        "key": "7",
        "value": "7"
    },
    {
        "term": 2,
        "command": "SET",
        "key": "8",
        "value": "8"
    },
    {
        "term": 17,
        "command": "NO-OP",
        "key": "None",
        "value": "None"
    }
]